PoreAnalyser/__init__.py
PoreAnalyser/conductance.py
PoreAnalyser/download_files.py
PoreAnalyser/hole_analysis.py
PoreAnalyser/poreanalyser.py
PoreAnalyser/visualization.py
PoreAnalyser/ProbeParticleEllipsoid/ellipse_lib.py
PoreAnalyser/ProbeParticleEllipsoid/ellipsoid_optimisation.py
PoreAnalyser/hole2/hole
PoreAnalyser/hole2/sos_triangle
PoreAnalyser/hole2/sph_process
PoreAnalyser/pdb_models/7tu9.pdb
PoreAnalyser/pdb_models/7tu9.pdb_ellipsoid.pdb
PoreAnalyser/pdb_models/7tu9_aligned_z.pdb
PoreAnalyser/pdb_models/7tu9_aligned_z.pdb100.pdb
PoreAnalyser/pdb_models/7tu9_aligned_z.pdb11.pdb
PoreAnalyser/pdb_models/7tu9_aligned_z.pdb12.pdb
PoreAnalyser/pdb_models/7tu9_aligned_z.pdb13.pdb
PoreAnalyser/pdb_models/7tu9_aligned_z.pdb14.pdb
PoreAnalyser/pdb_models/7tu9_aligned_z.pdb24.pdb
PoreAnalyser/pdb_models/7tu9_aligned_z.pdb37.pdb
PoreAnalyser/pdb_models/7tu9_aligned_z.pdb6.pdb
PoreAnalyser/pdb_models/7tu9_aligned_z.pdb8.pdb
PoreAnalyser/pdb_models/7tu9_aligned_z.pdb80.pdb
PoreAnalyser/pdb_models/7tu9_aligned_z.pdb9.pdb
PoreAnalyser/pdb_models/7tu9_aligned_z.pdb_ellipsoid.pdb
PoreAnalyser/pdb_models/7tu9_aligned_z.pdb_pathway_ellipse.txt
PoreAnalyser/pdb_models/7tu9a_aligned_z.pdb
PoreAnalyser/pdb_models/7tvi.pdb
PoreAnalyser/pdb_models/7tvi_aligned_z.pdb_pathway_ellipse.txt
PoreAnalyser/pdb_models/8fe1.pdb
PoreAnalyser/pdb_models/8fe1_aligned_z.pdb
PoreAnalyser/pdb_models/8fe1_aligned_z.pdb100.pdb
PoreAnalyser/pdb_models/8fe1_aligned_z.pdb_ellipsoid.pdb
PoreAnalyser/pdb_models/8fe1_aligned_z.pdb_pathway_ellipse.txt
PoreAnalyser/pdb_models/8fe1_aligned_z.s
PoreAnalyser/pdb_models/8fe1_aligned_z_aligned_z.pdb
PoreAnalyser/pdb_models/test_7tu9_aligned_z.pdb
PoreAnalyser/pdb_models/test_7tu9_aligned_z.sph
PoreAnalyser/tests/__init__.py
PoreAnalyser/tests/test_conductance.py
PoreAnalyser/tests/test_ellipse.py
PoreAnalyser/tests/test_ellipsoid_optimisation.py
PoreAnalyser/tests/test_hole.py
PoreAnalyser/tests/test_visualization.py
poreanalyser-0.0.12.dist-info/entry_points.txt
poreanalyser-0.0.12.dist-info/LICENSE
poreanalyser-0.0.12.dist-info/WHEEL
poreanalyser-0.0.12.dist-info/METADATA
poreanalyser-0.0.12.dist-info/RECORD
