Metadata-Version: 2.3
Name: PoreAnalyser
Version: 0.0.12
Summary: PoreAnalyser package based on HOLE and MDAnalysis
Author-email: David Seiferth <david.seiferth@oriel.ox.ac.uk>
Requires-Python: >=3.6,<3.13
Requires-Dist: numpy >=1.0
Requires-Dist: MDAnalysis >=2.0, <3.0
Requires-Dist: matplotlib>=0.1
Requires-Dist: pandas>=1.3
Requires-Dist: streamlit>=1.0
Requires-Dist: stmol==0.0.9
Requires-Dist: py3Dmol
Requires-Dist: ipyspeck==0.6.1
Requires-Dist: ipywidgets==7.6.3
Requires-Dist: scipy
Requires-Dist: altair<5
Requires-Dist: nglview
Requires-Dist: ipython_genutils==0.2.0
